llm_handler_validator-0.1.2.dist-info/METADATA
llm_handler_validator-0.1.2.dist-info/WHEEL
llm_handler_validator-0.1.2.dist-info/entry_points.txt
llmhandler/__init__.py
llmhandler/_internal_models.py
llmhandler/api_handler.py
llm_handler_validator-0.1.2.dist-info/RECORD
