Metadata-Version: 2.1
Name: llm_handler_validator
Version: 0.1.2
Summary: LLMHandler is a unified Python package that provides a single, consistent interface for interacting with multiple LLM providers, offering both structured (typed) and unstructured responses.
Author-Email: Bryan Nsoh <bryan.anye.5@gmail.com>
License: MIT
Project-URL: Homepage, https://github.com/BryanNsoh/LLMHandler
Project-URL: Source, https://github.com/BryanNsoh/LLMHandler
Requires-Python: >=3.9
Requires-Dist: pydantic>=2.10.6
Requires-Dist: aiolimiter>=1.2.1
Requires-Dist: pydantic-ai>=0.0.20
Requires-Dist: python-dotenv>=1.0.1
Requires-Dist: logfire>=3.4.0
